market_data_sdk/__init__.py
market_data_sdk/common/__init__.py
market_data_sdk/common/models/__init__.py
market_data_sdk/common/models/asset.py
market_data_sdk/epoch_polygon/__init__.py
market_data_sdk/epoch_polygon/client.py
market_data_sdk/epoch_polygon/registry.py
market_data_sdk/epoch_polygon/tools.py
market_data_sdk/epoch_polygon/clients/__init__.py
market_data_sdk/epoch_polygon/clients/agent_aggs_client.py
market_data_sdk/epoch_polygon/clients/agent_quotes_client.py
market_data_sdk/epoch_polygon/clients/agent_snapshot_client.py
market_data_sdk/epoch_polygon/clients/agent_trades_client.py
market_data_sdk/epoch_polygon/clients/base.py
market_data_sdk/epoch_polygon/models/__init__.py
market_data_sdk/epoch_polygon/models/asset.py
market_data_sdk/epoch_polygon/models/filters.py
market_data_sdk/epoch_polygon/models/requests.py
market_data_sdk/tradingeconomics/__init__.py
market_data_sdk/tradingeconomics/client.py
market_data_sdk/tradingeconomics/registry.py
market_data_sdk/tradingeconomics/clients/__init__.py
market_data_sdk/tradingeconomics/clients/base.py
market_data_sdk/tradingeconomics/clients/calendar.py
market_data_sdk/tradingeconomics/clients/forecasts.py
market_data_sdk/tradingeconomics/clients/indicators.py
market_data_sdk/tradingeconomics/clients/markets.py
market_data_sdk/tradingeconomics/clients/news.py
market_data_sdk/tradingeconomics/clients/reference.py
market_data_sdk/tradingeconomics/models/__init__.py
market_data_sdk/tradingeconomics/models/data.py
market_data_sdk/tradingeconomics/models/requests.py
market_data_sdk/tradingeconomics/tools/__init__.py
market_data_sdk/tradingeconomics/tools/calendar.py
market_data_sdk/tradingeconomics/tools/generate.py
market_data_sdk/tradingeconomics/tools/indicators.py
market_data_sdk-0.1.1.dist-info/METADATA
market_data_sdk-0.1.1.dist-info/WHEEL
market_data_sdk-0.1.1.dist-info/top_level.txt
market_data_sdk-0.1.1.dist-info/RECORD
