Metadata-Version: 2.4
Name: market-data-sdk
Version: 0.1.1
Summary: A unified SDK for Polygon and TradingEconomics with LangGraph integration
Home-page: https://github.com/epoch-labs/market-data-sdk
Author: Epoch Team
Author-email: Epoch Team <aadedewe@epoch.trade>
License: MIT
Project-URL: Homepage, https://github.com/epoch-labs/market-data-sdk
Requires-Python: >=3.8
Requires-Dist: langgraph-cli[inmem]
Requires-Dist: langgraph-sdk
Requires-Dist: langchain>=1.0.0a9
Requires-Dist: langchain-core
Requires-Dist: langchain-community
Requires-Dist: typing_extensions
Requires-Dist: polygon-api-client>=1.15.4
Requires-Dist: tradingeconomics>=0.3.0
Requires-Dist: pandas>=1.5.0
Requires-Dist: numpy>=1.21.0
Requires-Dist: python-dotenv>=0.19.0
Requires-Dist: requests>=2.28.0
Requires-Dist: aiohttp>=3.8.0
Requires-Dist: pydantic>=2.0.0
Provides-Extra: dev
Requires-Dist: pytest>=7.0.0; extra == "dev"
Requires-Dist: pytest-asyncio>=0.21.0; extra == "dev"
Requires-Dist: pytest-cov>=4.0.0; extra == "dev"
Requires-Dist: black>=22.0.0; extra == "dev"
Requires-Dist: flake8>=4.0.0; extra == "dev"
Requires-Dist: mypy>=0.950; extra == "dev"
Dynamic: author
Dynamic: home-page
Dynamic: requires-python
